lora_e22.py
lora_e22_constants.py
lora_e22_operation_constant.py
ebyte_lora_e22_rpi-0.0.4.dist-info/LICENSE.md
ebyte_lora_e22_rpi-0.0.4.dist-info/METADATA
ebyte_lora_e22_rpi-0.0.4.dist-info/WHEEL
ebyte_lora_e22_rpi-0.0.4.dist-info/top_level.txt
ebyte_lora_e22_rpi-0.0.4.dist-info/RECORD
