Metadata-Version: 2.1
Name: ebyte-lora-e22-rpi
Version: 0.0.4
Summary: RaspberryPi LoRa EBYTE E22 device library complete and tested. sx1262/sx1268
Home-page: https://github.com/xreef/EByte_LoRa_E22_raspberrypi_library
Author: Renzo Mischianti
Author-email: Renzo Mischianti <renzo@mischianti.org>
Maintainer: Renzo Mischianti
Maintainer-email: Renzo Mischianti <renzo@mischianti.org>
License: zThe MIT License (MIT)
Project-URL: homepage, https://www.mischianti.org
Project-URL: Documentation, https://www.mischianti.org/category/my-libraries/ebyte-lora-e22-devices/
Project-URL: Documentazione, https://www.mischianti.org/it/category/le-mie-librerie/dispositivi-ebyte-lora-e22/
Project-URL: Repository, https://github.com/xreef/EByte_LoRa_E22_raspberrypi_library
Project-URL: Bug Tracker, https://github.com/xreef/EByte_LoRa_E22_raspberrypi_library/issues
Project-URL: Examples, https://github.com/xreef/EByte_LoRa_E22_raspberrypi_library/tree/main/examples
Keywords: LoRa,UART,EByte,RaspberryPi,sx1262,sx1268,e22
Classifier: Development Status :: 5 - Production/Stable
Classifier: Programming Language :: Python
Classifier: License :: OSI Approved :: MIT License
Requires-Python: >=3.7
License-File: LICENSE.md
